AUTHORS.rst
CONTRIBUTING.rst
HISTORY.rst
LICENSE
MANIFEST.in
README.rst
setup.cfg
setup.py
docs/Makefile
docs/authors.rst
docs/conf.py
docs/contributing.rst
docs/history.rst
docs/index.rst
docs/installation.rst
docs/make.bat
docs/readme.rst
docs/usage.rst
qcenter/Master.py
qcenter/__init__.py
qcenter/test.py
qcenter.egg-info/PKG-INFO
qcenter.egg-info/SOURCES.txt
qcenter.egg-info/dependency_links.txt
qcenter.egg-info/entry_points.txt
qcenter.egg-info/not-zip-safe
qcenter.egg-info/requires.txt
qcenter.egg-info/top_level.txt
tests/__init__.py
tests/test_qcenter.py